odoo/addons/l10n_be_mis_reports_xml/README.rst
odoo/addons/l10n_be_mis_reports_xml/__init__.py
odoo/addons/l10n_be_mis_reports_xml/__manifest__.py
odoo/addons/l10n_be_mis_reports_xml/data/data.xml
odoo/addons/l10n_be_mis_reports_xml/i18n/l10n_be_mis_reports_xml.pot
odoo/addons/l10n_be_mis_reports_xml/models/__init__.py
odoo/addons/l10n_be_mis_reports_xml/models/mis_report_instance.py
odoo/addons/l10n_be_mis_reports_xml/readme/CONTRIBUTORS.md
odoo/addons/l10n_be_mis_reports_xml/readme/DESCRIPTION.md
odoo/addons/l10n_be_mis_reports_xml/readme/USAGE.md
odoo/addons/l10n_be_mis_reports_xml/reports/be_vat_declaration.xml
odoo/addons/l10n_be_mis_reports_xml/security/ir.model.access.csv
odoo/addons/l10n_be_mis_reports_xml/static/description/icon.png
odoo/addons/l10n_be_mis_reports_xml/static/description/index.html
odoo/addons/l10n_be_mis_reports_xml/tests/__init__.py
odoo/addons/l10n_be_mis_reports_xml/tests/test_l10n_be_mis_reports_xml.py
odoo/addons/l10n_be_mis_reports_xml/views/mis_report_instance.xml
odoo/addons/l10n_be_mis_reports_xml/wizards/__init__.py
odoo/addons/l10n_be_mis_reports_xml/wizards/be_vat_declaration_wizard.py
odoo/addons/l10n_be_mis_reports_xml/wizards/be_vat_declaration_wizard.xml
odoo_addon_l10n_be_mis_reports_xml-18.0.1.0.1.dist-info/METADATA
odoo_addon_l10n_be_mis_reports_xml-18.0.1.0.1.dist-info/WHEEL
odoo_addon_l10n_be_mis_reports_xml-18.0.1.0.1.dist-info/top_level.txt
odoo_addon_l10n_be_mis_reports_xml-18.0.1.0.1.dist-info/RECORD
