Metadata-Version: 2.1
Name: odoo-addon-l10n_be_mis_reports_xml
Version: 18.0.1.0.1
Requires-Python: >=3.10
Requires-Dist: odoo-addon-l10n_be_mis_reports==18.0.*
Requires-Dist: odoo-addon-report_xml==18.0.*
Requires-Dist: odoo==18.0.*
Summary: Exports MIS Builder templates VAT Declaration as XML to load on the administration websites.
Home-page: https://github.com/OCA/l10n-belgium
License: AGPL-3
Author: Coop IT Easy SC, Odoo Community Association (OCA)
Author-email: support@odoo-community.org
Classifier: Programming Language :: Python
Classifier: Framework :: Odoo
Classifier: Framework :: Odoo :: 18.0
Classifier: License :: OSI Approved :: GNU Affero General Public License v3
